cross_domain_saliency_maps/__init__.py
cross_domain_saliency_maps/tensorflow_ig/__init__.py
cross_domain_saliency_maps/tensorflow_ig/cross_domain_integrated_gradients.py
cross_domain_saliency_maps/tensorflow_ig/domain_transforms.py
cross_domain_saliency_maps/torch_ig/__init__.py
cross_domain_saliency_maps/torch_ig/cross_domain_integrated_gradients.py
cross_domain_saliency_maps/torch_ig/domain_transforms.py
cross_domain_saliency_maps-0.0.6.dist-info/METADATA
cross_domain_saliency_maps-0.0.6.dist-info/WHEEL
cross_domain_saliency_maps-0.0.6.dist-info/licenses/LICENSE
cross_domain_saliency_maps-0.0.6.dist-info/RECORD
