Metadata-Version: 2.4
Name: cross_domain_saliency_maps
Version: 0.0.6
Summary: Pytorch/Tensorflow package for generating saliency maps for time-series models using Cross-Domain Integrated Gradients.
Project-URL: Homepage, https://github.com/esl-epfl/cross-domain-saliency-maps
Author-email: Christodoulos Kechris <christodoulos.kechris@epfl.ch>
License-File: LICENSE
Keywords: explainable-ai,interpretability,pytorch,saliency-maps,tensorflow,time-series,xai
Classifier: License :: OSI Approved :: GNU General Public License v3 (GPLv3)
Classifier: Operating System :: OS Independent
Classifier: Programming Language :: Python :: 3
Requires-Python: >=3.10.16
Requires-Dist: tensorflow<=2.19,>=2.13.0
Requires-Dist: torch<=2.7,>=2.6.0
Requires-Dist: tqdm==4.67.1
